py_network_apis/__init__.py
py_network_apis/ipa_client.py
py_network_apis/libre_client.py
py_network_apis/netbox_client.py
py_network_apis/netbox_setup.py
py_network_apis/snmp_client.py
py_network_apis-0.0.2.dist-info/LICENSE
py_network_apis-0.0.2.dist-info/METADATA
py_network_apis-0.0.2.dist-info/WHEEL
py_network_apis-0.0.2.dist-info/top_level.txt
py_network_apis-0.0.2.dist-info/RECORD
